{
  "province": "安徽",
  "generated_at": "2026-06-25T13:29:16.008094",
  "pie": [],
  "radar": [
    {
      "name": "数据采集",
      "value": 0
    },
    {
      "name": "数字存档",
      "value": 0
    },
    {
      "name": "展示传播",
      "value": 0
    },
    {
      "name": "智慧管理",
      "value": 0
    },
    {
      "name": "AI应用",
      "value": 0
    },
    {
      "name": "数字保护",
      "value": 0
    }
  ],
  "bar": {
    "years": [
      2024,
      2025
    ],
    "counts": [
      1,
      3
    ],
    "amounts": [
      0.0,
      0.0
    ]
  },
  "top_museums": [
    {
      "name": "九华山风景区管理委员会文化旅游处",
      "count": 2
    },
    {
      "name": "安徽博物院（安徽省文物鉴定站）",
      "count": 1
    },
    {
      "name": "天长市博物馆",
      "count": 1
    }
  ],
  "top_suppliers": [
    {
      "name": "深圳市华图测控系统有限公司",
      "amount": 0.0
    },
    {
      "name": "武汉大势智慧科技有限公司",
      "amount": 0.0
    }
  ]
}