{
  "province": "四川",
  "total": 367,
  "total_scraped": 5,
  "matched": [
    {
      "name": "四川博物院",
      "level": "一级",
      "city": "",
      "scraped_name": "四川博物院",
      "confidence": 1.0
    },
    {
      "name": "四川广汉三星堆博物馆",
      "level": "一级",
      "city": "",
      "scraped_name": "四川广汉三星堆博物馆",
      "confidence": 1.0
    },
    {
      "name": "四川省夕佳山民俗博物馆",
      "level": "未定级",
      "city": "",
      "scraped_name": "四川省夕佳山民俗博物馆",
      "confidence": 1.0
    }
  ],
  "gap": [
    {
      "name": "成都博物馆（成都中国皮影博物馆）",
      "level": "一级",
      "city": ""
    },
    {
      "name": "成都杜甫草堂博物馆",
      "level": "一级",
      "city": ""
    },
    {
      "name": "成都金沙遗址博物馆",
      "level": "一级",
      "city": ""
    },
    {
      "name": "成都武侯祠博物馆",
      "level": "一级",
      "city": ""
    },
    {
      "name": "四川省建川博物馆",
      "level": "一级",
      "city": ""
    },
    {
      "name": "成都市青白江区博物馆",
      "level": "二级",
      "city": ""
    },
    {
      "name": "成都永陵博物馆",
      "level": "二级",
      "city": ""
    },
    {
      "name": "新都杨升庵博物馆",
      "level": "二级",
      "city": ""
    },
    {
      "name": "成都华希昆虫博物馆",
      "level": "二级",
      "city": ""
    },
    {
      "name": "成都许燎源现代设计艺术博物馆",
      "level": "二级",
      "city": ""
    },
    {
      "name": "成都市成华区拾野自然博物馆",
      "level": "二级",
      "city": ""
    },
    {
      "name": "崇州天演博物馆",
      "level": "二级",
      "city": ""
    },
    {
      "name": "彭州市博物馆",
      "level": "三级",
      "city": ""
    },
    {
      "name": "大邑县刘氏庄园博物馆",
      "level": "三级",
      "city": ""
    },
    {
      "name": "成都蜀锦织绣博物馆",
      "level": "三级",
      "city": ""
    },
    {
      "name": "四川易园园林艺术博物馆",
      "level": "三级",
      "city": ""
    },
    {
      "name": "成都川菜博物馆",
      "level": "三级",
      "city": ""
    },
    {
      "name": "成都三和老爷车博物馆",
      "level": "三级",
      "city": ""
    },
    {
      "name": "成都市李劼人故居纪念馆",
      "level": "未定级",
      "city": ""
    },
    {
      "name": "成都隋唐窑址博物馆",
      "level": "未定级",
      "city": ""
    },
    {
      "name": "成都画院书画博物馆",
      "level": "未定级",
      "city": ""
    },
    {
      "name": "成都市龙泉驿区博物馆",
      "level": "未定级",
      "city": ""
    },
    {
      "name": "成都市青白江区彭家珍大将军专祠纪念馆",
      "level": "未定级",
      "city": ""
    },
    {
      "name": "新都博物馆",
      "level": "未定级",
      "city": ""
    },
    {
      "name": "艾芜纪念馆",
      "level": "未定级",
      "city": ""
    },
    {
      "name": "成都市温江区博物馆",
      "level": "未定级",
      "city": ""
    },
    {
      "name": "王光祈纪念馆",
      "level": "未定级",
      "city": ""
    },
    {
      "name": "成都市郫都区博物馆",
      "level": "未定级",
      "city": ""
    },
    {
      "name": "成都市新津区纯阳观博物馆",
      "level": "未定级",
      "city": ""
    },
    {
      "name": "5·12抗震救灾纪念馆",
      "level": "未定级",
      "city": ""
    },
    {
      "name": "蒲江县博物馆",
      "level": "未定级",
      "city": ""
    },
    {
      "name": "都江堰市博物馆",
      "level": "未定级",
      "city": ""
    },
    {
      "name": "都江堰市青城山历史文化博物馆",
      "level": "未定级",
      "city": ""
    },
    {
      "name": "都江堰市抗震救灾和恢复重建陈列馆",
      "level": "未定级",
      "city": ""
    },
    {
      "name": "邛崃市博物馆",
      "level": "未定级",
      "city": ""
    },
    {
      "name": "邛崃市红军长征纪念馆",
      "level": "未定级",
      "city": ""
    },
    {
      "name": "崇州市博物馆",
      "level": "未定级",
      "city": ""
    },
    {
      "name": "明蜀王陵博物馆",
      "level": "未定级",
      "city": ""
    },
    {
      "name": "成都川剧艺术博物馆",
      "level": "未定级",
      "city": ""
    },
    {
      "name": "西南民族大学民族博物馆",
      "level": "未定级",
      "city": ""
    },
    {
      "name": "华西口腔医学博物馆",
      "level": "未定级",
      "city": ""
    },
    {
      "name": "成都直升机博物馆",
      "level": "未定级",
      "city": ""
    },
    {
      "name": "成都体育学院博物馆",
      "level": "未定级",
      "city": ""
    },
    {
      "name": "成都大熊猫博物馆",
      "level": "未定级",
      "city": ""
    },
    {
      "name": "巴金纪念馆",
      "level": "未定级",
      "city": ""
    },
    {
      "name": "成都饮食文化博物馆",
      "level": "未定级",
      "city": ""
    },
    {
      "name": "西部客家博物馆",
      "level": "未定级",
      "city": ""
    },
    {
      "name": "四川荣军博物馆",
      "level": "未定级",
      "city": ""
    },
    {
      "name": "成都中医药大学博物馆",
      "level": "未定级",
      "city": ""
    },
    {
      "name": "川藏公路博物馆",
      "level": "未定级",
      "city": ""
    },
    {
      "name": "四川新绿色中医药博物馆",
      "level": "未定级",
      "city": ""
    },
    {
      "name": "成都理工大学博物馆",
      "level": "未定级",
      "city": ""
    },
    {
      "name": "成都百家堂姓氏文化博物馆",
      "level": "未定级",
      "city": ""
    },
    {
      "name": "成都瑞鑫汉陶艺术博物馆",
      "level": "未定级",
      "city": ""
    },
    {
      "name": "成都蜀绣博物馆",
      "level": "未定级",
      "city": ""
    },
    {
      "name": "四川茂林博物馆",
      "level": "未定级",
      "city": ""
    },
    {
      "name": "成都朱成石刻艺术博物馆",
      "level": "未定级",
      "city": ""
    },
    {
      "name": "成都梦缘博物馆",
      "level": "未定级",
      "city": ""
    },
    {
      "name": "四川原道文化博物馆",
      "level": "未定级",
      "city": ""
    },
    {
      "name": "成都保前明清家具博物馆",
      "level": "未定级",
      "city": ""
    },
    {
      "name": "成都大吉喜马拉雅文化艺术博物馆",
      "level": "未定级",
      "city": ""
    },
    {
      "name": "成都龙海青铜镜博物馆",
      "level": "未定级",
      "city": ""
    },
    {
      "name": "成都和德儒玉器艺术博物馆",
      "level": "未定级",
      "city": ""
    },
    {
      "name": "成都市了凡木文化博物馆",
      "level": "未定级",
      "city": ""
    },
    {
      "name": "成都川江钱币博物馆",
      "level": "未定级",
      "city": ""
    },
    {
      "name": "成都泥邦陶瓷艺术博物馆",
      "level": "未定级",
      "city": ""
    },
    {
      "name": "成都标榜民间传统养生技艺博物馆",
      "level": "未定级",
      "city": ""
    },
    {
      "name": "成都市龙泉驿区艺大木质乐器博物馆",
      "level": "未定级",
      "city": ""
    },
    {
      "name": "成都标榜女红工艺博物馆",
      "level": "未定级",
      "city": ""
    },
    {
      "name": "成都川上雕塑艺术博物馆",
      "level": "未定级",
      "city": ""
    },
    {
      "name": "成都市龙泉驿区艺匠古籍文献修复技艺博物馆",
      "level": "未定级",
      "city": ""
    },
    {
      "name": "成都标榜川西古典家具博物馆",
      "level": "未定级",
      "city": ""
    },
    {
      "name": "四川南方丝绸之路博物馆",
      "level": "未定级",
      "city": ""
    },
    {
      "name": "四川建华芝麻油博物馆",
      "level": "未定级",
      "city": ""
    },
    {
      "name": "成都澄园书画艺术博物馆",
      "level": "未定级",
      "city": ""
    },
    {
      "name": "成都市人华奇石博物馆",
      "level": "未定级",
      "city": ""
    },
    {
      "name": "成都三邑川派盆景艺术博物馆",
      "level": "未定级",
      "city": ""
    },
    {
      "name": "成都毛家湾艺术博物馆",
      "level": "未定级",
      "city": ""
    },
    {
      "name": "成都市双流区汉轩民俗艺术博物馆",
      "level": "未定级",
      "city": ""
    },
    {
      "name": "四川省三都博物馆",
      "level": "未定级",
      "city": ""
    },
    {
      "name": "成都文清古蜀农耕文化博物馆",
      "level": "未定级",
      "city": ""
    },
    {
      "name": "成都市天府新区明昌博物馆",
      "level": "未定级",
      "city": ""
    },
    {
      "name": "四川天府荆溪茶具文化博物馆",
      "level": "未定级",
      "city": ""
    },
    {
      "name": "成都中药博物馆",
      "level": "未定级",
      "city": ""
    },
    {
      "name": "成都巴蜀汉陶艺术博物馆",
      "level": "未定级",
      "city": ""
    },
    {
      "name": "成都大华玉器博物馆",
      "level": "未定级",
      "city": ""
    },
    {
      "name": "四川省鹿野苑私立石刻艺术博物馆",
      "level": "未定级",
      "city": ""
    },
    {
      "name": "成都市郫都区大珍堂家具石刻艺术博物馆",
      "level": "未定级",
      "city": ""
    },
    {
      "name": "成都市郫都区望丛玉器博物馆",
      "level": "未定级",
      "city": ""
    },
    {
      "name": "成都市郫都区益园民俗博物馆",
      "level": "未定级",
      "city": ""
    },
    {
      "name": "成都市九百村奇石根雕博物馆",
      "level": "未定级",
      "city": ""
    },
    {
      "name": "成都蜀江博物馆",
      "level": "未定级",
      "city": ""
    },
    {
      "name": "成都香米园汉陶艺术博物馆",
      "level": "未定级",
      "city": ""
    },
    {
      "name": "成都文宝轩博物馆",
      "level": "未定级",
      "city": ""
    },
    {
      "name": "成都新岳艺术博物馆",
      "level": "未定级",
      "city": ""
    },
    {
      "name": "成都贺麟故居纪念馆",
      "level": "未定级",
      "city": ""
    },
    {
      "name": "蒲江明月轩篆刻艺术博物馆（传习所）",
      "level": "未定级",
      "city": ""
    },
    {
      "name": "成都乌木艺术博物馆",
      "level": "未定级",
      "city": ""
    },
    {
      "name": "成都皮影艺术博物馆",
      "level": "未定级",
      "city": ""
    },
    {
      "name": "都江堰青城金丝楠乌木艺术馆",
      "level": "未定级",
      "city": ""
    },
    {
      "name": "彭州市万木留香家具博物馆",
      "level": "未定级",
      "city": ""
    },
    {
      "name": "成都尔玛民俗博物馆",
      "level": "未定级",
      "city": ""
    },
    {
      "name": "成都华珍藏羌文化博物馆",
      "level": "未定级",
      "city": ""
    },
    {
      "name": "成都诚林金丝楠乌木博物馆",
      "level": "未定级",
      "city": ""
    },
    {
      "name": "邛崃市古韵博物馆",
      "level": "未定级",
      "city": ""
    },
    {
      "name": "邛崃市当代孝道文化博物馆",
      "level": "未定级",
      "city": ""
    },
    {
      "name": "成都水井坊博物馆",
      "level": "未定级",
      "city": ""
    },
    {
      "name": "成都绿舟博物馆",
      "level": "未定级",
      "city": ""
    },
    {
      "name": "成都立巢航空博物馆",
      "level": "未定级",
      "city": ""
    },
    {
      "name": "四川泰来古代艺术博物馆",
      "level": "未定级",
      "city": ""
    },
    {
      "name": "成都标榜古今发艺博物馆",
      "level": "未定级",
      "city": ""
    },
    {
      "name": "成都标榜当代土陶艺术博物馆",
      "level": "未定级",
      "city": ""
    },
    {
      "name": "成都市共品钱币博物馆",
      "level": "未定级",
      "city": ""
    },
    {
      "name": "自贡市盐业历史博物馆",
      "level": "一级",
      "city": ""
    },
    {
      "name": "自贡恐龙博物馆",
      "level": "一级",
      "city": ""
    },
    {
      "name": "自贡市中国彩灯博物馆",
      "level": "二级",
      "city": ""
    },
    {
      "name": "自贡抗日献金运动陈列馆",
      "level": "未定级",
      "city": ""
    },
    {
      "name": "邓萍故居陈列馆",
      "level": "未定级",
      "city": ""
    },
    {
      "name": "江姐故居陈列馆",
      "level": "未定级",
      "city": ""
    },
    {
      "name": "自贡抗战盐运文化陈列馆",
      "level": "未定级",
      "city": ""
    },
    {
      "name": "荣县吴玉章故居陈列馆",
      "level": "未定级",
      "city": ""
    },
    {
      "name": "荣县博物馆",
      "level": "未定级",
      "city": ""
    },
    {
      "name": "荣县军政府旧址陈列馆",
      "level": "未定级",
      "city": ""
    },
    {
      "name": "富顺县博物馆",
      "level": "未定级",
      "city": ""
    },
    {
      "name": "自贡博物院",
      "level": "未定级",
      "city": ""
    },
    {
      "name": "卢德铭故居陈列馆",
      "level": "未定级",
      "city": ""
    },
    {
      "name": "攀枝花中国三线建设博物馆（攀枝花市博物馆、攀枝花开发建设纪念馆）",
      "level": "二级",
      "city": ""
    },
    {
      "name": "攀枝花开发建设纪念馆",
      "level": "未定级",
      "city": ""
    },
    {
      "name": "攀枝花市西区初心园三线建设博物馆",
      "level": "未定级",
      "city": ""
    },
    {
      "name": "大田会议纪念馆",
      "level": "未定级",
      "city": ""
    },
    {
      "name": "攀枝花市仁和区博物馆(苴却砚博物馆）",
      "level": "未定级",
      "city": ""
    },
    {
      "name": "攀枝花市东区兰尖故事博物馆",
      "level": "未定级",
      "city": ""
    },
    {
      "name": "泸州市博物馆",
      "level": "二级",
      "city": ""
    },
    {
      "name": "四川泸县宋代石刻博物馆",
      "level": "二级",
      "city": ""
    },
    {
      "name": "古蔺县红军长征四渡赤水博物馆",
      "level": "三级",
      "city": ""
    },
    {
      "name": "泸州河川剧艺术博物馆",
      "level": "未定级",
      "city": ""
    },
    {
      "name": "泸州市古籍文献博物馆",
      "level": "未定级",
      "city": ""
    },
    {
      "name": "泸顺起义陈列馆",
      "level": "未定级",
      "city": ""
    },
    {
      "name": "况场朱德旧居陈列馆",
      "level": "未定级",
      "city": ""
    },
    {
      "name": "泸州石刻艺术博物馆",
      "level": "未定级",
      "city": ""
    },
    {
      "name": "蒋兆和故居陈列馆",
      "level": "未定级",
      "city": ""
    },
    {
      "name": "泸县屈氏庄园博物馆",
      "level": "未定级",
      "city": ""
    },
    {
      "name": "合江县汉代画像石棺博物馆",
      "level": "未定级",
      "city": ""
    },
    {
      "name": "叙永县木雕石刻艺术博物馆",
      "level": "未定级",
      "city": ""
    },
    {
      "name": "叙永县石厢子长征红色革命文化陈列馆",
      "level": "未定级",
      "city": ""
    },
    {
      "name": "古蔺县二郎滩渡口陈列馆",
      "level": "未定级",
      "city": ""
    },
    {
      "name": "西南医科大学附属中医医院中医药文化博物馆",
      "level": "未定级",
      "city": ""
    },
    {
      "name": "泸州老窖博物馆",
      "level": "未定级",
      "city": ""
    },
    {
      "name": "合江县王朝闻故居陈列馆",
      "level": "未定级",
      "city": ""
    },
    {
      "name": "泸州市纳溪区护国战争博物馆",
      "level": "未定级",
      "city": ""
    },
    {
      "name": "泸县民俗博物馆",
      "level": "未定级",
      "city": ""
    },
    {
      "name": "泸州市长江博物馆",
      "level": "未定级",
      "city": ""
    },
    {
      "name": "什邡市博物馆",
      "level": "三级",
      "city": ""
    },
    {
      "name": "绵竹市抗震救灾·灾后重建纪念馆",
      "level": "三级",
      "city": ""
    },
    {
      "name": "德阳市博物馆",
      "level": "未定级",
      "city": ""
    },
    {
      "name": "德阳市罗江区博物馆",
      "level": "未定级",
      "city": ""
    },
    {
      "name": "黄继光纪念馆（黄继光故居管理所）",
      "level": "未定级",
      "city": ""
    },
    {
      "name": "中江博物馆",
      "level": "未定级",
      "city": ""
    },
    {
      "name": "绵竹市博物馆",
      "level": "未定级",
      "city": ""
    },
    {
      "name": "绵竹年画博物馆",
      "level": "未定级",
      "city": ""
    },
    {
      "name": "德阳市罗江区庞统祠博物馆",
      "level": "未定级",
      "city": ""
    },
    {
      "name": "德阳市江奎艺术博物馆",
      "level": "未定级",
      "city": ""
    },
    {
      "name": "绵竹市李家大院民俗博物馆",
      "level": "未定级",
      "city": ""
    },
    {
      "name": "5·12汶川特大地震纪念馆",
      "level": "一级",
      "city": ""
    },
    {
      "name": "绵阳市博物馆",
      "level": "二级",
      "city": ""
    },
    {
      "name": "江油市李白纪念馆",
      "level": "二级",
      "city": ""
    },
    {
      "name": "绵阳市游仙区飞龙山红军纪念馆",
      "level": "未定级",
      "city": ""
    },
    {
      "name": "绵阳市安州区博物馆",
      "level": "未定级",
      "city": ""
    },
    {
      "name": "绵阳市安州区千佛山战役纪念馆",
      "level": "未定级",
      "city": ""
    },
    {
      "name": "三台县博物馆",
      "level": "未定级",
      "city": ""
    },
    {
      "name": "盐亭县博物馆",
      "level": "未定级",
      "city": ""
    },
    {
      "name": "梓潼县博物馆",
      "level": "未定级",
      "city": ""
    },
    {
      "name": "北川羌族自治县羌族民俗博物馆",
      "level": "未定级",
      "city": ""
    },
    {
      "name": "平武县历史博物馆",
      "level": "未定级",
      "city": ""
    },
    {
      "name": "江油市文物保护中心（江油市博物馆）",
      "level": "未定级",
      "city": ""
    },
    {
      "name": "江油市王右木纪念园",
      "level": "未定级",
      "city": ""
    },
    {
      "name": "平武报恩寺博物馆",
      "level": "未定级",
      "city": ""
    },
    {
      "name": "绵阳吉快艺术博物馆",
      "level": "未定级",
      "city": ""
    },
    {
      "name": "皇泽寺博物馆",
      "level": "三级",
      "city": ""
    },
    {
      "name": "广元市博物馆",
      "level": "未定级",
      "city": ""
    },
    {
      "name": "广元市红军文化博物馆",
      "level": "未定级",
      "city": ""
    },
    {
      "name": "广元市昭化区昭化汉城博物馆",
      "level": "未定级",
      "city": ""
    },
    {
      "name": "广元市昭化区博物馆（广元市昭化区汉城博物馆）",
      "level": "未定级",
      "city": ""
    },
    {
      "name": "陕南战役傲盘观战斗遗址陈列馆",
      "level": "未定级",
      "city": ""
    },
    {
      "name": "昭化古城红军革命遗址群陈列馆",
      "level": "未定级",
      "city": ""
    },
    {
      "name": "昭化区红四方面军指挥部旧址陈列馆",
      "level": "未定级",
      "city": ""
    },
    {
      "name": "昭化区虎跳红军渡口纪念馆",
      "level": "未定级",
      "city": ""
    },
    {
      "name": "昭化区太公山红军遗址群陈列馆",
      "level": "未定级",
      "city": ""
    },
    {
      "name": "广元市朝天区博物馆",
      "level": "未定级",
      "city": ""
    },
    {
      "name": "旺苍县木门军事会议纪念馆",
      "level": "未定级",
      "city": ""
    },
    {
      "name": "红三十一军军部旧址纪念馆",
      "level": "未定级",
      "city": ""
    },
    {
      "name": "红四方面军工农剧团旧址纪念馆",
      "level": "未定级",
      "city": ""
    },
    {
      "name": "红四方面军总指挥部旧址纪念馆",
      "level": "三级",
      "city": ""
    },
    {
      "name": "青川县地震博物馆",
      "level": "未定级",
      "city": ""
    },
    {
      "name": "青川县博物馆",
      "level": "未定级",
      "city": ""
    },
    {
      "name": "大路河红军石刻标语陈列馆",
      "level": "未定级",
      "city": ""
    },
    {
      "name": "红军攻克剑门关纪念馆",
      "level": "未定级",
      "city": ""
    },
    {
      "name": "红四方面军剑阁陈列馆",
      "level": "未定级",
      "city": ""
    },
    {
      "name": "红四方面军马鞍山纪念馆",
      "level": "未定级",
      "city": ""
    },
    {
      "name": "火烧寺战斗陈列馆",
      "level": "未定级",
      "city": ""
    },
    {
      "name": "剑阁县博物馆",
      "level": "未定级",
      "city": ""
    },
    {
      "name": "苍溪县红四方面军长征出发地纪念馆",
      "level": "未定级",
      "city": ""
    },
    {
      "name": "苍溪黄猫垭战斗遗址纪念馆",
      "level": "未定级",
      "city": ""
    },
    {
      "name": "苍溪苏维埃政府旧址纪念馆",
      "level": "未定级",
      "city": ""
    },
    {
      "name": "广元市千佛崖石刻艺术博物馆",
      "level": "未定级",
      "city": ""
    },
    {
      "name": "广元市朝天地震陈列馆",
      "level": "未定级",
      "city": ""
    },
    {
      "name": "蜀道文化博物馆",
      "level": "未定级",
      "city": ""
    },
    {
      "name": "广元万安博物馆",
      "level": "未定级",
      "city": ""
    },
    {
      "name": "遂宁市博物馆",
      "level": "二级",
      "city": ""
    },
    {
      "name": "射洪市书画博物馆",
      "level": "三级",
      "city": ""
    },
    {
      "name": "遂宁市安居区区博物馆（区文物保护所）",
      "level": "未定级",
      "city": ""
    },
    {
      "name": "蓬溪书法艺术博物馆",
      "level": "未定级",
      "city": ""
    },
    {
      "name": "大英县汉陶博物馆",
      "level": "未定级",
      "city": ""
    },
    {
      "name": "遂宁观音文化博物馆",
      "level": "未定级",
      "city": ""
    },
    {
      "name": "遂宁市安居人家博物馆",
      "level": "未定级",
      "city": ""
    },
    {
      "name": "内江市张大千纪念馆",
      "level": "三级",
      "city": ""
    },
    {
      "name": "范长江纪念馆",
      "level": "未定级",
      "city": ""
    },
    {
      "name": "内江市博物馆",
      "level": "未定级",
      "city": ""
    },
    {
      "name": "威远县罗世文烈士史料陈列馆",
      "level": "未定级",
      "city": ""
    },
    {
      "name": "资中县博物馆",
      "level": "未定级",
      "city": ""
    },
    {
      "name": "资中县罗泉会议会址陈列馆",
      "level": "未定级",
      "city": ""
    },
    {
      "name": "乐山崖墓博物馆",
      "level": "未定级",
      "city": ""
    },
    {
      "name": "乐山文庙博物馆",
      "level": "未定级",
      "city": ""
    },
    {
      "name": "沙湾郭沫若故居纪念馆",
      "level": "未定级",
      "city": ""
    },
    {
      "name": "乐山市金口河铁道兵博物馆",
      "level": "未定级",
      "city": ""
    },
    {
      "name": "四川夹江手工造纸博物馆",
      "level": "未定级",
      "city": ""
    },
    {
      "name": "峨眉山市博物馆",
      "level": "未定级",
      "city": ""
    },
    {
      "name": "峨眉山博物馆",
      "level": "未定级",
      "city": ""
    },
    {
      "name": "犍为县文庙博物馆",
      "level": "未定级",
      "city": ""
    },
    {
      "name": "乐山市博物馆",
      "level": "未定级",
      "city": ""
    },
    {
      "name": "夹江县收音机博物馆",
      "level": "未定级",
      "city": ""
    },
    {
      "name": "乐山乌木珍品文化博物馆",
      "level": "未定级",
      "city": ""
    },
    {
      "name": "朱德同志故居纪念馆",
      "level": "一级",
      "city": ""
    },
    {
      "name": "朱德铜像纪念园",
      "level": "三级",
      "city": ""
    },
    {
      "name": "罗瑞卿纪念馆",
      "level": "未定级",
      "city": ""
    },
    {
      "name": "张澜纪念馆",
      "level": "未定级",
      "city": ""
    },
    {
      "name": "南部县长坪山红军纪念馆",
      "level": "未定级",
      "city": ""
    },
    {
      "name": "南部县文物博物馆",
      "level": "未定级",
      "city": ""
    },
    {
      "name": "仪陇县博物馆",
      "level": "未定级",
      "city": ""
    },
    {
      "name": "张思德纪念馆",
      "level": "未定级",
      "city": ""
    },
    {
      "name": "红九军政治部旧址陈列馆",
      "level": "未定级",
      "city": ""
    },
    {
      "name": "张思德故居陈列室",
      "level": "未定级",
      "city": ""
    },
    {
      "name": "西充县博物馆",
      "level": "未定级",
      "city": ""
    },
    {
      "name": "阆中市博物馆",
      "level": "未定级",
      "city": ""
    },
    {
      "name": "阆中市红军烈士纪念园",
      "level": "未定级",
      "city": ""
    },
    {
      "name": "南充博物院（南充市文物保护中心）",
      "level": "未定级",
      "city": ""
    },
    {
      "name": "西充县民主同盟历史陈列馆",
      "level": "未定级",
      "city": ""
    },
    {
      "name": "四川王皮影艺术博物馆",
      "level": "未定级",
      "city": ""
    },
    {
      "name": "阆中丝毯博物馆",
      "level": "未定级",
      "city": ""
    },
    {
      "name": "眉山三苏祠博物馆",
      "level": "二级",
      "city": ""
    },
    {
      "name": "丹棱县大雅堂博物馆",
      "level": "三级",
      "city": ""
    },
    {
      "name": "眉山三苏纪念馆",
      "level": "未定级",
      "city": ""
    },
    {
      "name": "彭山博物馆（眉山市彭山区汉崖墓博物馆）",
      "level": "未定级",
      "city": ""
    },
    {
      "name": "彭山博物馆",
      "level": "未定级",
      "city": ""
    },
    {
      "name": "洪雅县民俗台会博物馆",
      "level": "未定级",
      "city": ""
    },
    {
      "name": "东坡泡菜博物馆",
      "level": "未定级",
      "city": ""
    },
    {
      "name": "四川监狱博物馆",
      "level": "未定级",
      "city": ""
    },
    {
      "name": "青神竹编博物馆",
      "level": "未定级",
      "city": ""
    },
    {
      "name": "宜宾市博物院",
      "level": "二级",
      "city": ""
    },
    {
      "name": "宜宾市赵一曼纪念馆",
      "level": "三级",
      "city": ""
    },
    {
      "name": "宜宾市翠屏区李庄抗战文化陈列馆",
      "level": "未定级",
      "city": ""
    },
    {
      "name": "李庄文化抗战博物馆",
      "level": "未定级",
      "city": ""
    },
    {
      "name": "宜宾市南溪朱德旧居陈列馆",
      "level": "未定级",
      "city": ""
    },
    {
      "name": "宜宾市南溪区博物馆",
      "level": "未定级",
      "city": ""
    },
    {
      "name": "宜宾市叙州区博物馆",
      "level": "未定级",
      "city": ""
    },
    {
      "name": "国立剧专史料江安陈列馆",
      "level": "未定级",
      "city": ""
    },
    {
      "name": "宜宾市蜀南竹海博物馆",
      "level": "未定级",
      "city": ""
    },
    {
      "name": "中共川南特委陈列馆",
      "level": "未定级",
      "city": ""
    },
    {
      "name": "高县阳翰笙纪念馆",
      "level": "未定级",
      "city": ""
    },
    {
      "name": "珙县博物馆",
      "level": "未定级",
      "city": ""
    },
    {
      "name": "兴文县博物馆",
      "level": "未定级",
      "city": ""
    },
    {
      "name": "屏山县综合博物馆",
      "level": "未定级",
      "city": ""
    },
    {
      "name": "高县李硕勋烈士纪念馆",
      "level": "未定级",
      "city": ""
    },
    {
      "name": "宜宾市南溪区农慧民俗馆",
      "level": "未定级",
      "city": ""
    },
    {
      "name": "宜宾市静观石博物馆",
      "level": "未定级",
      "city": ""
    },
    {
      "name": "邓小平故居陈列馆",
      "level": "一级",
      "city": ""
    },
    {
      "name": "广安市博物馆",
      "level": "未定级",
      "city": ""
    },
    {
      "name": "邻水县博物馆",
      "level": "未定级",
      "city": ""
    },
    {
      "name": "毕占云生平事迹陈列馆",
      "level": "未定级",
      "city": ""
    },
    {
      "name": "华蓥山起义女战士陈列馆",
      "level": "未定级",
      "city": ""
    },
    {
      "name": "上川东地工委禄市特支陈列馆",
      "level": "未定级",
      "city": ""
    },
    {
      "name": "武胜县宝箴塞民俗博物馆",
      "level": "未定级",
      "city": ""
    },
    {
      "name": "达州市博物馆",
      "level": "二级",
      "city": ""
    },
    {
      "name": "渠县历史博物馆",
      "level": "三级",
      "city": ""
    },
    {
      "name": "达州红军文化陈列馆",
      "level": "未定级",
      "city": ""
    },
    {
      "name": "宣汉县王维舟纪念馆",
      "level": "未定级",
      "city": ""
    },
    {
      "name": "开江县博物馆",
      "level": "未定级",
      "city": ""
    },
    {
      "name": "渠县汉阙文化博物馆",
      "level": "未定级",
      "city": ""
    },
    {
      "name": "川陕革命根据地万源保卫战战史陈列馆",
      "level": "未定级",
      "city": ""
    },
    {
      "name": "达州钢琴博物馆",
      "level": "未定级",
      "city": ""
    },
    {
      "name": "雅安市博物馆",
      "level": "二级",
      "city": ""
    },
    {
      "name": "荥经县博物馆",
      "level": "二级",
      "city": ""
    },
    {
      "name": "雅安市雨城区博物馆",
      "level": "未定级",
      "city": ""
    },
    {
      "name": "雅安市生态博物馆",
      "level": "未定级",
      "city": ""
    },
    {
      "name": "蒙顶山茶史博物馆",
      "level": "未定级",
      "city": ""
    },
    {
      "name": "汉源县博物馆",
      "level": "未定级",
      "city": ""
    },
    {
      "name": "石棉县中国工农红军强渡大渡河纪念馆",
      "level": "未定级",
      "city": ""
    },
    {
      "name": "川矿记忆陈列馆",
      "level": "未定级",
      "city": ""
    },
    {
      "name": "天全县红军纪念馆",
      "level": "未定级",
      "city": ""
    },
    {
      "name": "天全县红色文化陈列馆",
      "level": "未定级",
      "city": ""
    },
    {
      "name": "“4·20”芦山强烈地震纪念馆",
      "level": "未定级",
      "city": ""
    },
    {
      "name": "芦山县博物馆",
      "level": "未定级",
      "city": ""
    },
    {
      "name": "宝兴县红军翻越夹金山纪念馆",
      "level": "未定级",
      "city": ""
    },
    {
      "name": "宝兴县博物馆",
      "level": "未定级",
      "city": ""
    },
    {
      "name": "雅安市名山区红军百丈关战斗遗址陈列馆",
      "level": "未定级",
      "city": ""
    },
    {
      "name": "雅安市骑士罗骑行游历博物馆",
      "level": "未定级",
      "city": ""
    },
    {
      "name": "川陕苏区将帅碑林纪念馆",
      "level": "三级",
      "city": ""
    },
    {
      "name": "川陕革命根据地博物馆",
      "level": "三级",
      "city": ""
    },
    {
      "name": "红四方面军总指挥部旧址纪念馆",
      "level": "三级",
      "city": ""
    },
    {
      "name": "南江县博物馆",
      "level": "三级",
      "city": ""
    },
    {
      "name": "巴中市巴州区晏阳初博物馆",
      "level": "未定级",
      "city": ""
    },
    {
      "name": "巴中市巴州区历史文化博物馆",
      "level": "未定级",
      "city": ""
    },
    {
      "name": "通江银耳博物馆",
      "level": "未定级",
      "city": ""
    },
    {
      "name": "巴山民俗文化博物馆",
      "level": "未定级",
      "city": ""
    },
    {
      "name": "川陕苏区纪念馆",
      "level": "未定级",
      "city": ""
    },
    {
      "name": "川陕苏区苦草坝后勤中心旧址陈列馆",
      "level": "未定级",
      "city": ""
    },
    {
      "name": "红江县政治保卫局旧址陈列馆",
      "level": "未定级",
      "city": ""
    },
    {
      "name": "红四方面军总医院旧址陈列馆",
      "level": "未定级",
      "city": ""
    },
    {
      "name": "毛浴坝会议会址陈列馆",
      "level": "未定级",
      "city": ""
    },
    {
      "name": "通江县空山战役纪念馆",
      "level": "未定级",
      "city": ""
    },
    {
      "name": "巴山游击队纪念馆",
      "level": "未定级",
      "city": ""
    },
    {
      "name": "南江县长赤苏维埃政府旧址陈列馆",
      "level": "未定级",
      "city": ""
    },
    {
      "name": "平昌县刘伯坚纪念馆",
      "level": "未定级",
      "city": ""
    },
    {
      "name": "川陕苏区平昌县革命文物陈列馆",
      "level": "未定级",
      "city": ""
    },
    {
      "name": "光雾山-诺水河地质公园博物馆",
      "level": "未定级",
      "city": ""
    },
    {
      "name": "陈毅纪念馆",
      "level": "三级",
      "city": ""
    },
    {
      "name": "资阳市博物馆",
      "level": "未定级",
      "city": ""
    },
    {
      "name": "汶川县博物馆",
      "level": "三级",
      "city": ""
    },
    {
      "name": "“5·12”汶川特大地震映秀震中纪念馆",
      "level": "三级",
      "city": ""
    },
    {
      "name": "茂县羌族博物馆",
      "level": "三级",
      "city": ""
    },
    {
      "name": "黑水县芦花会议会址陈列馆",
      "level": "未定级",
      "city": ""
    },
    {
      "name": "马尔康红军长征纪念馆",
      "level": "未定级",
      "city": ""
    },
    {
      "name": "汶川县马岭山红军阻击战场遗址纪念馆",
      "level": "未定级",
      "city": ""
    },
    {
      "name": "理县博物馆",
      "level": "未定级",
      "city": ""
    },
    {
      "name": "红军长征纪念馆",
      "level": "未定级",
      "city": ""
    },
    {
      "name": "毛儿盖会议会址陈列馆",
      "level": "未定级",
      "city": ""
    },
    {
      "name": "沙窝会议会址陈列馆",
      "level": "未定级",
      "city": ""
    },
    {
      "name": "松潘红军长征过草地陈列馆",
      "level": "未定级",
      "city": ""
    },
    {
      "name": "九寨沟县博物馆",
      "level": "未定级",
      "city": ""
    },
    {
      "name": "金川县红五军军部旧址陈列馆",
      "level": "未定级",
      "city": ""
    },
    {
      "name": "小金县红军长征两河口会议纪念馆",
      "level": "未定级",
      "city": ""
    },
    {
      "name": "达维会师陈列馆",
      "level": "未定级",
      "city": ""
    },
    {
      "name": "若尔盖县巴西纪念馆",
      "level": "未定级",
      "city": ""
    },
    {
      "name": "阿坝州博物馆",
      "level": "未定级",
      "city": ""
    },
    {
      "name": "卧龙自然与地震博物馆",
      "level": "未定级",
      "city": ""
    },
    {
      "name": "昌列博物馆",
      "level": "未定级",
      "city": ""
    },
    {
      "name": "维强羌族银饰博物馆",
      "level": "未定级",
      "city": ""
    },
    {
      "name": "甘孜藏族自治州民族博物馆",
      "level": "未定级",
      "city": ""
    },
    {
      "name": "红军飞夺泸定桥纪念馆",
      "level": "未定级",
      "city": ""
    },
    {
      "name": "炉霍博物馆",
      "level": "未定级",
      "city": ""
    },
    {
      "name": "朱德总司令和五世格达活佛纪念馆",
      "level": "未定级",
      "city": ""
    },
    {
      "name": "色达县格萨尔文化博物馆",
      "level": "未定级",
      "city": ""
    },
    {
      "name": "凉山彝族奴隶社会博物馆",
      "level": "三级",
      "city": ""
    },
    {
      "name": "知识青年上山下乡西昌纪念馆",
      "level": "未定级",
      "city": ""
    },
    {
      "name": "红军长征礼州会议陈列馆",
      "level": "未定级",
      "city": ""
    },
    {
      "name": "德昌县博物馆",
      "level": "未定级",
      "city": ""
    },
    {
      "name": "会理县红军长征纪念馆",
      "level": "未定级",
      "city": ""
    },
    {
      "name": "会理市红军长征巧渡金沙江陈列馆",
      "level": "未定级",
      "city": ""
    },
    {
      "name": "会理市会理会议陈列馆",
      "level": "未定级",
      "city": ""
    },
    {
      "name": "冕宁县红军长征纪念馆",
      "level": "未定级",
      "city": ""
    },
    {
      "name": "彝海结盟纪念馆",
      "level": "未定级",
      "city": ""
    },
    {
      "name": "凉山彝族自治州博物馆",
      "level": "未定级",
      "city": ""
    },
    {
      "name": "盐源摩梭博物馆",
      "level": "未定级",
      "city": ""
    }
  ],
  "uncertain": [
    {
      "name": "四川大学博物馆",
      "level": "未定级",
      "scraped_name": "四川大学",
      "confidence": 0.51
    }
  ]
}