{
  "province": "山东",
  "total": 3,
  "total_scraped": 3,
  "matched": [
    {
      "name": "山东博物馆",
      "level": "",
      "city": "",
      "scraped_name": "山东博物馆",
      "confidence": 1.0
    },
    {
      "name": "山东省文物考古研究院",
      "level": "",
      "city": "",
      "scraped_name": "山东省文物考古研究院",
      "confidence": 1.0
    },
    {
      "name": "无棣县文物保护中心",
      "level": "",
      "city": "滨州市",
      "scraped_name": "无棣县文物保护中心",
      "confidence": 1.0
    }
  ],
  "gap": [],
  "uncertain": []
}